{"nama":{"0":"TK NEGERI CIDDAI CITTA","1":"TK AL-GHASHIYA   ","2":"TK ATIKA 2 TANACELLAE","3":"TK ATIKA PKK LABAE","4":"KB AISYIYAH II TOCAKKO","5":"KB NUR SYAFAA AT PKK KAMPIRI","6":"KB NURUL FAUZIAH","7":"KB VIOLA","8":"KB. AL- KHAERAT","9":"KB. NUR IKHLAS AISYIYAH I","10":"SD NEGERI 259 TANACELLAE","11":"SD NEGERI 269 ALLANGKIANGENG","12":"SD NEGERI 93 TANETE","13":"SD NEGERI 94 KAMPIRI","14":"SD NEGERI 95 KECCEE","15":"SD NEGERI 96 CITTA","16":"SD NEGERI 97 UNGAE","17":"SD NEGERI 99 LABAE","18":"SMP NEGERI 4 LILIRIAJA","19":"SMP NEGERI 5 LILIRIAJA","20":"SMP SATAP Negeri LabaE"},"sekolah_id":{"0":"CA997FA4-BBCB-457C-A388-C8576628F7C4","1":"D0EC8955-60F1-4972-940E-324129D39D5C","2":"F843C9FA-5C46-4CED-9E60-E1043BAB0661","3":"F76A4B7B-D482-48BB-8F41-C43BB2F40534","4":"D912FCB2-B9B8-46AF-B28D-78F334D86FA9","5":"C0285E29-669E-4FAB-B82E-DA43E8A60452","6":"639FF6DD-AB71-4480-B6DE-6BDD6A9FB6EE","7":"C541B485-C56B-49FB-A90A-16047826D850","8":"4FA74493-039F-466A-9BAA-48D45EF01541","9":"D93E7A8F-003B-4A91-A588-5F8164CA6F18","10":"2089C8BC-0D26-E111-A858-67D504835B05","11":"A0D1C8BC-0D26-E111-90A5-DBA2C71383F9","12":"20D2C4BC-0D26-E111-A305-EF13E6D64734","13":"E0F9C4BC-0D26-E111-A6B4-05E144A1F3AF","14":"D027C5BC-0D26-E111-A0D0-9726E1FB6539","15":"2059C5BC-0D26-E111-89BC-412252818389","16":"6084C5BC-0D26-E111-9283-E9A3AEA69819","17":"30B4C5BC-0D26-E111-B474-A5367485DED8","18":"F0F84DC0-0D26-E111-B81C-9DE0E7BB5CBD","19":"901050C0-0D26-E111-8EB4-2FBBFECB5EA1","20":"E08CE849-82FE-E111-BCDD-115638F811D5"},"npsn":{"0":40314713,"1":69971747,"2":69966481,"3":40314714,"4":69776070,"5":69830152,"6":70005046,"7":69974179,"8":69830163,"9":69776069,"10":40303630,"11":40303571,"12":40303739,"13":40303740,"14":40303741,"15":40303732,"16":40303731,"17":40303722,"18":40303677,"19":40314253,"20":40314310},"jumlah_kirim":{"0":12,"1":0,"2":0,"3":6,"4":3,"5":0,"6":1,"7":0,"8":1,"9":3,"10":0,"11":4,"12":8,"13":9,"14":7,"15":3,"16":4,"17":2,"18":21,"19":11,"20":13},"ptk":{"0":5,"1":3,"2":1,"3":3,"4":3,"5":3,"6":3,"7":1,"8":3,"9":3,"10":10,"11":8,"12":10,"13":8,"14":7,"15":10,"16":7,"17":9,"18":13,"19":10,"20":8},"pegawai":{"0":2,"1":1,"2":1,"3":1,"4":2,"5":1,"6":1,"7":1,"8":1,"9":1,"10":3,"11":2,"12":2,"13":2,"14":3,"15":2,"16":4,"17":1,"18":4,"19":2,"20":2},"pd":{"0":59,"1":0,"2":0,"3":34,"4":21,"5":0,"6":12,"7":0,"8":24,"9":28,"10":0,"11":57,"12":77,"13":60,"14":60,"15":109,"16":60,"17":59,"18":124,"19":70,"20":38},"rombel":{"0":5,"1":0,"2":0,"3":3,"4":2,"5":0,"6":2,"7":0,"8":2,"9":2,"10":0,"11":6,"12":6,"13":6,"14":6,"15":6,"16":6,"17":6,"18":6,"19":3,"20":3},"jml_rk":{"0":5,"1":0,"2":0,"3":2,"4":2,"5":0,"6":2,"7":0,"8":2,"9":2,"10":0,"11":6,"12":6,"13":6,"14":5,"15":12,"16":6,"17":6,"18":7,"19":6,"20":8},"jml_lab":{"0":0,"1":0,"2":0,"3":0,"4":0,"5":0,"6":0,"7":0,"8":0,"9":0,"10":0,"11":1,"12":0,"13":0,"14":0,"15":1,"16":0,"17":0,"18":2,"19":2,"20":1},"jml_perpus":{"0":0,"1":0,"2":0,"3":0,"4":0,"5":0,"6":0,"7":0,"8":0,"9":0,"10":0,"11":1,"12":1,"13":1,"14":1,"15":1,"16":1,"17":1,"18":1,"19":1,"20":1},"induk_kecamatan":{"0":"Kec. Citta","1":"Kec. Citta","2":"Kec. Citta","3":"Kec. Citta","4":"Kec. Citta","5":"Kec. Citta","6":"Kec. Citta","7":"Kec. Citta","8":"Kec. Citta","9":"Kec. Citta","10":"Kec. Citta","11":"Kec. Citta","12":"Kec. Citta","13":"Kec. Citta","14":"Kec. Citta","15":"Kec. Citta","16":"Kec. Citta","17":"Kec. Citta","18":"Kec. Citta","19":"Kec. Citta","20":"Kec. Citta"},"kode_wilayah_induk_kecamatan":{"0":"190908  ","1":"190908  ","2":"190908  ","3":"190908  ","4":"190908  ","5":"190908  ","6":"190908  ","7":"190908  ","8":"190908  ","9":"190908  ","10":"190908  ","11":"190908  ","12":"190908  ","13":"190908  ","14":"190908  ","15":"190908  ","16":"190908  ","17":"190908  ","18":"190908  ","19":"190908  ","20":"190908  "},"induk_kabupaten":{"0":"Kab. Soppeng","1":"Kab. Soppeng","2":"Kab. Soppeng","3":"Kab. Soppeng","4":"Kab. Soppeng","5":"Kab. Soppeng","6":"Kab. Soppeng","7":"Kab. Soppeng","8":"Kab. Soppeng","9":"Kab. Soppeng","10":"Kab. Soppeng","11":"Kab. Soppeng","12":"Kab. Soppeng","13":"Kab. Soppeng","14":"Kab. Soppeng","15":"Kab. Soppeng","16":"Kab. Soppeng","17":"Kab. Soppeng","18":"Kab. Soppeng","19":"Kab. Soppeng","20":"Kab. Soppeng"},"kode_wilayah_induk_kabupaten":{"0":"190900  ","1":"190900  ","2":"190900  ","3":"190900  ","4":"190900  ","5":"190900  ","6":"190900  ","7":"190900  ","8":"190900  ","9":"190900  ","10":"190900  ","11":"190900  ","12":"190900  ","13":"190900  ","14":"190900  ","15":"190900  ","16":"190900  ","17":"190900  ","18":"190900  ","19":"190900  ","20":"190900  "},"induk_provinsi":{"0":"Prov. Sulawesi Selatan","1":"Prov. Sulawesi Selatan","2":"Prov. Sulawesi Selatan","3":"Prov. Sulawesi Selatan","4":"Prov. Sulawesi Selatan","5":"Prov. Sulawesi Selatan","6":"Prov. Sulawesi Selatan","7":"Prov. Sulawesi Selatan","8":"Prov. Sulawesi Selatan","9":"Prov. Sulawesi Selatan","10":"Prov. Sulawesi Selatan","11":"Prov. Sulawesi Selatan","12":"Prov. Sulawesi Selatan","13":"Prov. Sulawesi Selatan","14":"Prov. Sulawesi Selatan","15":"Prov. Sulawesi Selatan","16":"Prov. Sulawesi Selatan","17":"Prov. Sulawesi Selatan","18":"Prov. Sulawesi Selatan","19":"Prov. Sulawesi Selatan","20":"Prov. Sulawesi Selatan"},"kode_wilayah_induk_provinsi":{"0":"190000  ","1":"190000  ","2":"190000  ","3":"190000  ","4":"190000  ","5":"190000  ","6":"190000  ","7":"190000  ","8":"190000  ","9":"190000  ","10":"190000  ","11":"190000  ","12":"190000  ","13":"190000  ","14":"190000  ","15":"190000  ","16":"190000  ","17":"190000  ","18":"190000  ","19":"190000  ","20":"190000  "},"bentuk_pendidikan":{"0":"TK","1":"TK","2":"TK","3":"TK","4":"KB","5":"KB","6":"KB","7":"KB","8":"KB","9":"KB","10":"SD","11":"SD","12":"SD","13":"SD","14":"SD","15":"SD","16":"SD","17":"SD","18":"SMP","19":"SMP","20":"SMP"},"status_sekolah":{"0":"Negeri","1":"Swasta","2":"Swasta","3":"Swasta","4":"Swasta","5":"Swasta","6":"Swasta","7":"Swasta","8":"Swasta","9":"Swasta","10":"Negeri","11":"Negeri","12":"Negeri","13":"Negeri","14":"Negeri","15":"Negeri","16":"Negeri","17":"Negeri","18":"Negeri","19":"Negeri","20":"Negeri"},"sinkron_terakhir":{"0":"17 Jan 2024 15:02:25","1":"24 Aug 2023 14:09:33","2":"20 Nov 2023 20:17:03","3":"22 Jan 2024 11:07:23","4":"02 Feb 2024 19:06:39","5":"14 Nov 2023 07:29:17","6":"03 Feb 2024 07:47:39","7":"25 Oct 2023 11:12:38","8":"27 Jan 2024 06:55:15","9":"05 Feb 2024 20:56:16","10":"10 Oct 2023 17:49:50","11":"03 Feb 2024 08:54:42","12":"25 Jan 2024 08:34:48","13":"24 Jan 2024 07:45:21","14":"26 Jan 2024 13:15:08","15":"31 Jan 2024 11:36:46","16":"31 Jan 2024 09:18:21","17":"18 Jan 2024 09:13:52","18":"31 Jan 2024 07:48:10","19":"06 Feb 2024 14:12:38","20":"30 Jan 2024 08:45:16"},"sekolah_id_enkrip":{"0":"556FB08018A1589F8C97                                                                                ","1":"11ACEDD04E368118E8BF                                                                                ","2":"CFA32A13F2E3B99CD077                                                                                ","3":"50E1F1A6089D641B36B6                                                                                ","4":"B5D35F4A103992DBF1B8                                                                                ","5":"CDE3B664B4FAF2124EB4                                                                                ","6":"9D89A529F34619B25F64                                                                                ","7":"4A37A96481F24A89F452                                                                                ","8":"1320D61EBFF5FEFCE2AB                                                                                ","9":"2536D23BEEF02EDF1466                                                                                ","10":"EA0DF52DE2D75F51131A                                                                                ","11":"8DD6698E2643B106B770                                                                                ","12":"A53DEE96943BFA3FE93D                                                                                ","13":"619A2A2A4D2B312A9C5F                                                                                ","14":"487FE4C0859F7A22A58F                                                                                ","15":"35D328A81D772570748A                                                                                ","16":"8F2FBF2EC1F2993043FE                                                                                ","17":"25D3927336F2572AC7B7                                                                                ","18":"D05532370E58A1AB9176                                                                                ","19":"E172D10FE050E5FD91D0                                                                                ","20":"14AE5A36565247E7C320                                                                                "}}